{
  "foods": [
    {
      "id": 1,
      "name": "Veggie",
      "description": "Macarrão com pimentão, ervilha e ervas finas colhidas no himalaia.",
      "price": "26.90",
      "available": true,
      "image": "https://storage.googleapis.com/golden-wind/bootcamp-gostack/desafio-food/food2.png"
    },
    {
      "id": 2,
      "name": "A La Camarón",
      "description": "Macarrão com vegetais de primeira linha e camarão dos 7 mares.",
      "price": "40.20",
      "available": true,
      "image": "https://storage.googleapis.com/golden-wind/bootcamp-gostack/desafio-food/food3.png"
    },
    {
      "id": 3,
      "name": "Veggie",
      "description": "Macarrão com pimentão, ervilha e ervas finas colhidas no himalaia.",
      "price": "29.90",
      "available": true,
      "image": "https://storage.googleapis.com/golden-wind/bootcamp-gostack/desafio-food/food2.png"
    },
    {
      "name": "A La Camarón",
      "image": "https://storage.googleapis.com/golden-wind/bootcamp-gostack/desafio-food/food3.png",
      "price": "32.50",
      "description": "Macarrão com vegetais de primeira linha e camarão dos 7 mares.",
      "available": true,
      "id": 4
    },
    {
      "name": "A La Camarón",
      "image": "https://storage.googleapis.com/golden-wind/bootcamp-gostack/desafio-food/food3.png",
      "price": "32.50",
      "description": "Macarrão com vegetais de primeira linha e camarão dos 7 mares.",
      "available": true,
      "id": 6
    },
    {
      "name": "A La Camarón",
      "image": "https://storage.googleapis.com/golden-wind/bootcamp-gostack/desafio-food/food3.png",
      "price": "32.50",
      "description": "Macarrão com vegetais de primeira linha e camarão dos 7 mares.",
      "available": true,
      "id": 8
    },
    {
      "id": 9,
      "name": "Veggie",
      "description": "Macarrão com pimentão, ervilha e ervas finas colhidas no himalaia.",
      "price": "29.90",
      "available": true,
      "image": "https://storage.googleapis.com/golden-wind/bootcamp-gostack/desafio-food/food2.png"
    },
    {
      "name": "A La Camarón",
      "image": "https://storage.googleapis.com/golden-wind/bootcamp-gostack/desafio-food/food3.png",
      "price": "32.50",
      "description": "Macarrão com vegetais de primeira linha e camarão dos 7 mares.",
      "available": true,
      "id": 10
    },
    {
      "id": 11,
      "name": "Veggie",
      "description": "Macarrão com pimentão, ervilha e ervas finas colhidas no himalaia.",
      "price": "29.90",
      "available": true,
      "image": "https://storage.googleapis.com/golden-wind/bootcamp-gostack/desafio-food/food2.png"
    },
    {
      "name": "A La Camarón",
      "image": "https://storage.googleapis.com/golden-wind/bootcamp-gostack/desafio-food/food3.png",
      "price": "32.50",
      "description": "Macarrão com vegetais de primeira linha e camarão dos 7 mares.",
      "available": true,
      "id": 12
    },
    {
      "id": 13,
      "name": "Veggie",
      "description": "Macarrão com pimentão, ervilha e ervas finas colhidas no himalaia.",
      "price": "29.90",
      "available": true,
      "image": "https://storage.googleapis.com/golden-wind/bootcamp-gostack/desafio-food/food2.png"
    },
    {
      "name": "A La Camarón",
      "image": "https://storage.googleapis.com/golden-wind/bootcamp-gostack/desafio-food/food3.png",
      "price": "32.50",
      "description": "Macarrão com vegetais de primeira linha e camarão dos 7 mares.",
      "available": true,
      "id": 14
    },
    {
      "name": "Pizza Italiana",
      "image": "https://cdn.pixabay.com/photo/2017/12/09/08/18/pizza-3007395_960_720.jpg",
      "price": "45.90",
      "description": "Moda Italiana direto de Roma.",
      "available": true,
      "id": 15
    }
  ]
}